<?xml version="1.0" encoding="UTF-8" standalone="yes"?><orders><order><orderId>111000245795</orderId><profileId>82851588</profileId><orderState>PROCESSING</orderState><createdByOrder></createdByOrder><originOfOrder>default</originOfOrder><createdDate>2019/05/22:21:39</createdDate><submittedDate>2019/07/18:00:24</submittedDate><lastModifiedDate>2019/07/18:00:26</lastModifiedDate><completedDate></completedDate><agentID></agentID><salesChannel>0</salesChannel><siteId>612</siteId><isAssociateUser>0</isAssociateUser><associateNumber></associateNumber><IPAddress>173.95.85.163</IPAddress><couponCode></couponCode><userEmailAddress>abby.ross@comcast.net</userEmailAddress><international>false</international><storeAssocLogin></storeAssocLogin><storeAssocStoreId></storeAssocStoreId><storeAssocReason></storeAssocReason><itemPriceOverridden>0</itemPriceOverridden><shipPriceOverridden>0</shipPriceOverridden><priceInfo><type>orderPriceInfo</type><orderPriceInfo><rawSubtotal>102.99</rawSubtotal><tax>6.72</tax><shipping>8.95</shipping></orderPriceInfo><currencyCode>USD</currencyCode><amount>102.99</amount><discounted>false</discounted><amountIsFinal>false</amountIsFinal><fullPrice>0.0</fullPrice><nonFullPrice>0.0</nonFullPrice></priceInfo><commerceItem><commerceItemId>ici3507105563</commerceItemId><type>commerceItem</type><productType>default</productType><catalogRefId>26561042</catalogRefId><quantity>1</quantity><finalSale>false</finalSale><giftCardStatus>NoAction</giftCardStatus><message></message><priceInfo><itemPriceInfo><quantityDiscounted>0</quantityDiscounted><salePrice>0.0</salePrice><listPrice>59.5</listPrice><onSale>false</onSale><rawTotalPrice>59.5</rawTotalPrice><orderDiscountShare>0.0</orderDiscountShare></itemPriceInfo><detailedItemPriceInfo><quantity>1</quantity><orderDiscountShare>0.0</orderDiscountShare><tax>3.56</tax><orderManualAdjustmentShare>0.0</orderManualAdjustmentShare></detailedItemPriceInfo><amount>59.5</amount><discounted>false</discounted><amountIsFinal>false</amountIsFinal><fullPrice>0.0</fullPrice><nonFullPrice>0.0</nonFullPrice><adjustments><adjustmentDescription>List price</adjustmentDescription><totalAdjustment>59.5</totalAdjustment><quantityAdjusted>1</quantityAdjusted></adjustments></priceInfo><coupons/><catalogId></catalogId><catalogKey>en_US</catalogKey><productId>493113</productId><state>PROCESSING</state><stateDetail></stateDetail><order_ref>111000245795</order_ref><lastmodified>2019-07-18 00:10:10</lastmodified><maxSVSCalls>0</maxSVSCalls><giftBoxed>false</giftBoxed><messageTo></messageTo><messageFrom></messageFrom><partnerId></partnerId></commerceItem><commerceItem><commerceItemId>ici3507105564</commerceItemId><type>commerceItem</type><productType>default</productType><catalogRefId>26646275</catalogRefId><quantity>1</quantity><finalSale>false</finalSale><giftCardStatus>NoAction</giftCardStatus><message></message><priceInfo><itemPriceInfo><quantityDiscounted>1</quantityDiscounted><salePrice>0.0</salePrice><listPrice>39.5</listPrice><onSale>false</onSale><rawTotalPrice>39.5</rawTotalPrice><orderDiscountShare>0.0</orderDiscountShare></itemPriceInfo><detailedItemPriceInfo><quantity>1</quantity><orderDiscountShare>0.0</orderDiscountShare><tax>1.2</tax><orderManualAdjustmentShare>0.0</orderManualAdjustmentShare></detailedItemPriceInfo><amount>20.0</amount><discounted>true</discounted><amountIsFinal>false</amountIsFinal><fullPrice>0.0</fullPrice><nonFullPrice>0.0</nonFullPrice><adjustments><adjustmentDescription>List price</adjustmentDescription><totalAdjustment>39.5</totalAdjustment><quantityAdjusted>1</quantityAdjusted></adjustments><adjustments><adjustmentDescription>Item Discount</adjustmentDescription><totalAdjustment>-19.5</totalAdjustment><quantityAdjusted>1</quantityAdjusted></adjustments></priceInfo><coupons/><catalogId></catalogId><catalogKey>en_US</catalogKey><productId>488398</productId><state>PROCESSING</state><stateDetail></stateDetail><order_ref>111000245795</order_ref><lastmodified>2019-07-18 00:10:10</lastmodified><maxSVSCalls>0</maxSVSCalls><giftBoxed>false</giftBoxed><messageTo></messageTo><messageFrom></messageFrom><partnerId></partnerId></commerceItem><commerceItem><commerceItemId>ici3507105612</commerceItemId><type>commerceItem</type><productType>default</productType><catalogRefId>27600559</catalogRefId><quantity>1</quantity><finalSale>false</finalSale><giftCardStatus>NoAction</giftCardStatus><message></message><priceInfo><itemPriceInfo><quantityDiscounted>1</quantityDiscounted><salePrice>46.99</salePrice><listPrice>79.5</listPrice><onSale>true</onSale><rawTotalPrice>79.5</rawTotalPrice><orderDiscountShare>0.0</orderDiscountShare></itemPriceInfo><detailedItemPriceInfo><quantity>1</quantity><orderDiscountShare>0.0</orderDiscountShare><tax>1.41</tax><orderManualAdjustmentShare>0.0</orderManualAdjustmentShare></detailedItemPriceInfo><amount>23.49</amount><discounted>true</discounted><amountIsFinal>false</amountIsFinal><fullPrice>0.0</fullPrice><nonFullPrice>0.0</nonFullPrice><adjustments><adjustmentDescription>List price</adjustmentDescription><totalAdjustment>79.5</totalAdjustment><quantityAdjusted>1</quantityAdjusted></adjustments><adjustments><adjustmentDescription>Sale price</adjustmentDescription><totalAdjustment>-32.51</totalAdjustment><quantityAdjusted>1</quantityAdjusted></adjustments><adjustments><adjustmentDescription>Item Discount</adjustmentDescription><totalAdjustment>-23.5</totalAdjustment><quantityAdjusted>1</quantityAdjusted></adjustments></priceInfo><coupons/><catalogId></catalogId><catalogKey>en_US</catalogKey><productId>502438</productId><state>PROCESSING</state><stateDetail></stateDetail><order_ref>111000245795</order_ref><lastmodified>2019-07-18 00:12:57</lastmodified><maxSVSCalls>0</maxSVSCalls><giftBoxed>false</giftBoxed><messageTo></messageTo><messageFrom></messageFrom><partnerId></partnerId></commerceItem><paymentGroup><paymentGroupId>ipg722436515</paymentGroupId><payPal><tenderType>paypal</tenderType><tenderSubType>paypal</tenderSubType><payerId>YZQQYTRMF6K7S</payerId><transactionId>d74wdc03</transactionId><billingAddress><prefix></prefix><firstName>Abby</firstName><middleName></middleName><lastName>Ross</lastName><suffix></suffix><companyName></companyName><jobTitle></jobTitle><poBox></poBox><address1>1522 Orlando Road</address1><address2></address2><address3></address3><city>Parkville</city><country>US</country><postalCode>21234</postalCode><email>abby.ross@comcast.net</email><phoneNumber>4434720996</phoneNumber><stateAddress>MD</stateAddress><county></county><faxNumber></faxNumber></billingAddress></payPal><amountCredited>0.0</amountCredited><amount>118.66</amount><paymentMethod>paypal</paymentMethod><submittedDate>2019/07/18:00:24</submittedDate><currencyCode>USD</currencyCode><state>AUTHORIZED</state><paymentGroupClassType>paypal</paymentGroupClassType><amountAuthorized>118.66</amountAuthorized><amountDebited>0.0</amountDebited><stateDetail></stateDetail><specialInstructions></specialInstructions><authorizationStatus>1</authorizationStatus><debitStatus></debitStatus><creditStatus></creditStatus><preAuthCompleteCalls>0</preAuthCompleteCalls></paymentGroup><shippingGroup><shippingGroupId>isg998754019</shippingGroupId><shippingMethod>Standard</shippingMethod><description>Address:Standard</description><shipOnDate></shipOnDate><actualShipDate></actualShipDate><state>PROCESSING</state><stateDetail></stateDetail><submittedDate></submittedDate><priceInfo><shippingPriceInfo><rawShipping>8.95</rawShipping><shippingTax>0.55</shippingTax></shippingPriceInfo></priceInfo><order>111000245795</order><specialInstructions></specialInstructions><type>1</type><hardgoodShippingGroup><trackingNumber></trackingNumber><pickupType>STH</pickupType><storeNum></storeNum><shippingAddress><prefix></prefix><firstName>Abby</firstName><middleName></middleName><lastName>Spilker</lastName><suffix></suffix><companyName></companyName><jobTitle></jobTitle><poBox></poBox><address1>1522 Orlando Rd</address1><address2></address2><address3></address3><city>Parkville</city><stateAddress>MD</stateAddress><country>US</country><postalCode>21234</postalCode><email></email><phoneNumber>4434720996</phoneNumber><county></county><faxNumber></faxNumber></shippingAddress></hardgoodShippingGroup><electronicShippingGroup><email></email></electronicShippingGroup></shippingGroup><relationship><type>payOrderRel</type><payOrderRel><paymentGroupId>ipg722436515</paymentGroupId><orderRef>111000245795</orderRef><amount>118.66</amount></payOrderRel></relationship><relationship><type>shipItemRel</type><shipItemRel><shippingGroupId>isg998754019</shippingGroupId><commerceItemId>ici3507105563</commerceItemId><quantity>1</quantity><returnedQuantity>0</returnedQuantity><amount>0.0</amount><state>INITIAL</state><stateDetail></stateDetail><lowBound>0</lowBound><highBound>0</highBound><shortShippedQuantity>0</shortShippedQuantity><egcNumber></egcNumber><trackingDetails/></shipItemRel></relationship><relationship><type>shipItemRel</type><shipItemRel><shippingGroupId>isg998754019</shippingGroupId><commerceItemId>ici3507105564</commerceItemId><quantity>1</quantity><returnedQuantity>0</returnedQuantity><amount>0.0</amount><state>INITIAL</state><stateDetail></stateDetail><lowBound>0</lowBound><highBound>0</highBound><shortShippedQuantity>0</shortShippedQuantity><egcNumber></egcNumber><trackingDetails/></shipItemRel></relationship><relationship><type>shipItemRel</type><shipItemRel><shippingGroupId>isg998754019</shippingGroupId><commerceItemId>ici3507105612</commerceItemId><quantity>1</quantity><returnedQuantity>0</returnedQuantity><amount>0.0</amount><state>INITIAL</state><stateDetail></stateDetail><lowBound>0</lowBound><highBound>0</highBound><shortShippedQuantity>0</shortShippedQuantity><egcNumber></egcNumber><trackingDetails/></shipItemRel></relationship><partnerId></partnerId><loyaltyId></loyaltyId></order></orders>