[
  {
    "mode": "NULLABLE", 
    "name": "if_entry_no", 
    "type": "INTEGER"
  }, 
  {
    "mode": "NULLABLE", 
    "name": "interface_control_flag", 
    "type": "INTEGER"
  }, 
  {
    "mode": "NULLABLE", 
    "name": "record_type", 
    "type": "STRING"
  }, 
  {
    "mode": "NULLABLE", 
    "name": "store_no", 
    "type": "INTEGER"
  }, 
  {
    "mode": "NULLABLE", 
    "name": "register_no", 
    "type": "INTEGER"
  }, 
  {
    "mode": "NULLABLE", 
    "name": "transaction_date", 
    "type": "STRING"
  }, 
  {
    "mode": "NULLABLE", 
    "name": "entry_date_time", 
    "type": "STRING"
  }, 
  {
    "mode": "NULLABLE", 
    "name": "transaction_series", 
    "type": "STRING"
  }, 
  {
    "mode": "NULLABLE", 
    "name": "transaction_no", 
    "type": "INTEGER"
  }, 
  {
    "mode": "NULLABLE", 
    "name": "cashier_no", 
    "type": "INTEGER"
  }, 
  {
    "mode": "NULLABLE", 
    "name": "transaction_category", 
    "type": "INTEGER"
  }, 
  {
    "mode": "NULLABLE", 
    "name": "tender_total", 
    "type": "NUMERIC"
  }, 
  {
    "mode": "NULLABLE", 
    "name": "transaction_void_flag", 
    "type": "INTEGER"
  }, 
  {
    "mode": "NULLABLE", 
    "name": "exception_flag", 
    "type": "INTEGER"
  }, 
  {
    "mode": "NULLABLE", 
    "name": "deposit_declaration_flag", 
    "type": "INTEGER"
  }, 
  {
    "mode": "NULLABLE", 
    "name": "closeout_flag", 
    "type": "INTEGER"
  }, 
  {
    "mode": "NULLABLE", 
    "name": "media_count_flag", 
    "type": "INTEGER"
  }, 
  {
    "mode": "NULLABLE", 
    "name": "tax_override_flag", 
    "type": "INTEGER"
  }, 
  {
    "mode": "NULLABLE", 
    "name": "pos_tax_jurisdiction", 
    "type": "STRING"
  }, 
  {
    "mode": "NULLABLE", 
    "name": "employee_no", 
    "type": "INTEGER"
  }, 
  {
    "mode": "NULLABLE", 
    "name": "transaction_remark", 
    "type": "STRING"
  }, 
  {
    "mode": "NULLABLE", 
    "name": "updated_by_user_name", 
    "type": "STRING"
  }, 
  {
    "mode": "NULLABLE", 
    "name": "company_no", 
    "type": "INTEGER"
  }, 
  {
    "mode": "NULLABLE", 
    "name": "till_no", 
    "type": "NUMERIC"
  }, 
  {
    "mode": "NULLABLE", 
    "name": "batch_id", 
    "type": "INTEGER"
  }
]
