
[
{"mode": "NULLABLE", "name": "CHAIN_NBR"                     , "type": "STRING"},
{"mode": "NULLABLE", "name": "FISCAL_WEEK_NBR"               , "type": "STRING"},
{"mode": "NULLABLE", "name": "SUBCLASS_NBR"                  , "type": "STRING"},
{"mode": "NULLABLE", "name": "MERCH_CHANNEL_TYPE_CD"         , "type": "STRING"},
{"mode": "NULLABLE", "name": "PLAN_CHANNEL_TYPE_CD"          , "type": "STRING"},
{"mode": "NULLABLE", "name": "PLAN_VERSION_NBR"              , "type": "STRING"},
{"mode": "NULLABLE", "name": "MERCH_PLAN_TYPE_CD"            , "type": "STRING"},
{"mode": "NULLABLE", "name": "PLAN_INITIAL_MARKUP_RTL"       , "type": "STRING"},
{"mode": "NULLABLE", "name": "PLAN_ON_ORDER_QTY"             , "type": "STRING"},
{"mode": "NULLABLE", "name": "PLAN_ON_ORDER_RTL"             , "type": "STRING"},
{"mode": "NULLABLE", "name": "PLAN_ON_ORDER_CST"             , "type": "STRING"},
{"mode": "NULLABLE", "name": "PLAN_DC_RECEIPTS_QTY"          , "type": "STRING"},
{"mode": "NULLABLE", "name": "PLAN_DC_RECEIPTS_RTL"          , "type": "STRING"},
{"mode": "NULLABLE", "name": "PLAN_DC_RECEIPTS_CST"          , "type": "STRING"},
{"mode": "NULLABLE", "name": "PLAN_DC_BOP_QTY"               , "type": "STRING"},
{"mode": "NULLABLE", "name": "PLAN_DC_BOP_RTL"               , "type": "STRING"},
{"mode": "NULLABLE", "name": "PLAN_DC_BOP_CST"               , "type": "STRING"},
{"mode": "NULLABLE", "name": "PLAN_DC_ON_HAND_QTY"           , "type": "STRING"},
{"mode": "NULLABLE", "name": "PLAN_DC_ON_HAND_RTL"           , "type": "STRING"},
{"mode": "NULLABLE", "name": "PLAN_DC_ON_HAND_CST"           , "type": "STRING"},
{"mode": "NULLABLE", "name": "PLAN_DC_DISTRIBUTED_OUT_QTY"   , "type": "STRING"},
{"mode": "NULLABLE", "name": "PLAN_DC_DISTRIBUTED_OUT_RTL"   , "type": "STRING"},
{"mode": "NULLABLE", "name": "PLAN_DC_DISTRIBUTED_OUT_CST"   , "type": "STRING"},
{"mode": "NULLABLE", "name": "PLAN_DC_PERM_MARKDOWN_QTY"     , "type": "STRING"},
{"mode": "NULLABLE", "name": "PLAN_DC_PERM_MARKDOWN_RTL"     , "type": "STRING"},
{"mode": "NULLABLE", "name": "PLAN_DC_PERM_MARKDOWN_CST"     , "type": "STRING"},
{"mode": "NULLABLE", "name": "PLAN_DC_ADJUSTMENT_QTY"        , "type": "STRING"},
{"mode": "NULLABLE", "name": "PLAN_DC_ADJUSTMENT_RTL"        , "type": "STRING"},
{"mode": "NULLABLE", "name": "PLAN_DC_ADJUSTMENT_CST"        , "type": "STRING"},
{"mode": "NULLABLE", "name": "PLAN_DC_SHRINK_QTY"            , "type": "STRING"},
{"mode": "NULLABLE", "name": "PLAN_DC_SHRINK_RTL"            , "type": "STRING"},
{"mode": "NULLABLE", "name": "PLAN_DC_SHRINK_CST"            , "type": "STRING"},
{"mode": "NULLABLE", "name": "PLAN_IN_TRANSIT_QTY"           , "type": "STRING"},
{"mode": "NULLABLE", "name": "PLAN_IN_TRANSIT_RTL"           , "type": "STRING"},
{"mode": "NULLABLE", "name": "PLAN_IN_TRANSIT_CST"           , "type": "STRING"},
{"mode": "NULLABLE", "name": "PLAN_STORE_RECEIPTS_QTY"       , "type": "STRING"},
{"mode": "NULLABLE", "name": "PLAN_STORE_RECEIPTS_RTL"       , "type": "STRING"},
{"mode": "NULLABLE", "name": "PLAN_STORE_RECEIPTS_CST"       , "type": "STRING"},
{"mode": "NULLABLE", "name": "PLAN_STORE_BOP_QTY"            , "type": "STRING"},
{"mode": "NULLABLE", "name": "PLAN_STORE_BOP_RTL"            , "type": "STRING"},
{"mode": "NULLABLE", "name": "PLAN_STORE_BOP_CST"            , "type": "STRING"},
{"mode": "NULLABLE", "name": "PLAN_STORE_COUNT_QTY"          , "type": "STRING"},
{"mode": "NULLABLE", "name": "PLAN_STORE_ON_HAND_QTY"        , "type": "STRING"},
{"mode": "NULLABLE", "name": "PLAN_STORE_ON_HAND_RTL"        , "type": "STRING"},
{"mode": "NULLABLE", "name": "PLAN_STORE_ON_HAND_CST"        , "type": "STRING"},
{"mode": "NULLABLE", "name": "PLAN_STORE_SALES_QTY"          , "type": "STRING"},
{"mode": "NULLABLE", "name": "PLAN_STORE_SALES_RTL"          , "type": "STRING"},
{"mode": "NULLABLE", "name": "PLAN_STORE_SALES_CST"          , "type": "STRING"},
{"mode": "NULLABLE", "name": "PLAN_MARKUP_INITIAL"           , "type": "STRING"},
{"mode": "NULLABLE", "name": "PLAN_MARKUP_QTY"               , "type": "STRING"},
{"mode": "NULLABLE", "name": "PLAN_MARKUP_RTL"               , "type": "STRING"},
{"mode": "NULLABLE", "name": "PLAN_MARKUP_CST"               , "type": "STRING"},
{"mode": "NULLABLE", "name": "PLAN_STORE_PERM_MARKDOWN_QTY"  , "type": "STRING"},
{"mode": "NULLABLE", "name": "PLAN_STORE_PERM_MARKDOWN_RTL"  , "type": "STRING"},
{"mode": "NULLABLE", "name": "PLAN_STORE_PERM_MARKDOWN_CST"  , "type": "STRING"},
{"mode": "NULLABLE", "name": "PLAN_STORE_PROMO_MARKDOWN_QTY" , "type": "STRING"},
{"mode": "NULLABLE", "name": "PLAN_STORE_PROMO_MARKDOWN_RTL" , "type": "STRING"},
{"mode": "NULLABLE", "name": "PLAN_STORE_PROMO_MARKDOWN_CST" , "type": "STRING"},
{"mode": "NULLABLE", "name": "PLAN_STORE_SHRINK_QTY"         , "type": "STRING"},
{"mode": "NULLABLE", "name": "PLAN_STORE_SHRINK_RTL"         , "type": "STRING"},
{"mode": "NULLABLE", "name": "PLAN_STORE_SHRINK_CST"         , "type": "STRING"},
{"mode": "NULLABLE", "name": "PLAN_STORE_ADJUSTMENT_QTY"     , "type": "STRING"},
{"mode": "NULLABLE", "name": "PLAN_STORE_ADJUSTMENT_RTL"     , "type": "STRING"},
{"mode": "NULLABLE", "name": "PLAN_STORE_ADJUSTMENT_CST"     , "type": "STRING"},
{"mode": "NULLABLE", "name": "PLAN_TOTAL_BOP_QTY"            , "type": "STRING"},
{"mode": "NULLABLE", "name": "PLAN_TOTAL_BOP_RTL"            , "type": "STRING"},
{"mode": "NULLABLE", "name": "PLAN_TOTAL_BOP_CST"            , "type": "STRING"},
{"mode": "NULLABLE", "name": "PLAN_TOTAL_ON_HAND_QTY"        , "type": "STRING"},
{"mode": "NULLABLE", "name": "PLAN_TOTAL_ON_HAND_RTL"        , "type": "STRING"},
{"mode": "NULLABLE", "name": "PLAN_TOTAL_ON_HAND_CST"        , "type": "STRING"},
{"mode": "NULLABLE", "name": "PLAN_EROSION_FACTOR_QTY"       , "type": "STRING"},
{"mode": "NULLABLE", "name": "PLAN_EROSION_FACTOR_RTL"       , "type": "STRING"},
{"mode": "NULLABLE", "name": "PLAN_EROSION_FACTOR_CST"       , "type": "STRING"},
{"mode": "NULLABLE", "name": "PLAN_EROSION_QTY"              , "type": "STRING"},
{"mode": "NULLABLE", "name": "PLAN_EROSION_RTL"              , "type": "STRING"},
{"mode": "NULLABLE", "name": "PLAN_EROSION_CST"              , "type": "STRING"},
{"mode": "NULLABLE", "name": "PLAN_STORES_CST"               , "type": "STRING"},
{"mode": "NULLABLE", "name": "PLAN_ADDITIONAL_MARKUP_RTL"    , "type": "STRING"},
{"mode": "NULLABLE", "name": "PLAN_ADDITIONAL_MARKUP_CST"    , "type": "STRING"},
{"mode": "NULLABLE", "name": "PLAN_ADDITIONAL_MARKUP_QTY"    , "type": "STRING"},
{"mode": "NULLABLE", "name": "CHAIN_PLAN_TYPE_DESC"          , "type": "STRING"},
{"mode": "NULLABLE", "name": "LAST_UPDATE_TS"                , "type": "STRING"},
{"mode": "NULLABLE", "name": "EXTRACT_TS"                    , "type": "STRING"}
]

